dmol/__init__.py
dmol_book-1.3.2.dist-info/METADATA
dmol_book-1.3.2.dist-info/WHEEL
dmol_book-1.3.2.dist-info/top_level.txt
dmol_book-1.3.2.dist-info/RECORD
