Metadata-Version: 2.1
Name: dmol-book
Version: 1.3.2
Summary: Style and Imports for dmol Book
Home-page: https://dmol.pub
Author: Andrew D White
Author-email: andrew.white@rochester.edu
License: MIT
Classifier: Programming Language :: Python :: 3
Classifier: License :: OSI Approved :: MIT License
Classifier: Operating System :: OS Independent
Classifier: Topic :: Scientific/Engineering :: Chemistry
Classifier: Topic :: Scientific/Engineering :: Artificial Intelligence
Classifier: Typing :: Typed
Requires-Dist: jupyter-book (==0.13.1)
Requires-Dist: matplotlib
Requires-Dist: numpy
Requires-Dist: ipython (!=8.7.0jax)
Requires-Dist: jaxlib
Requires-Dist: pandas
Requires-Dist: tensorflow (>=2.7)
Requires-Dist: seaborn
Requires-Dist: tabulate
Requires-Dist: scikit-learn
Requires-Dist: pydot
Requires-Dist: pillow (>=8.3.2)
Requires-Dist: mordred[full]
Requires-Dist: moviepy
Requires-Dist: networkx
Requires-Dist: MDAnalysis
Requires-Dist: emlp (==1.0.2)
Requires-Dist: tensorflow-probability
Requires-Dist: dm-haiku
Requires-Dist: selfies
Requires-Dist: tensorflowjs
Requires-Dist: exmol
Requires-Dist: rdkit (>=2022)
Requires-Dist: sympy
Requires-Dist: e3nn
Requires-Dist: torch (==1.12)
Requires-Dist: simpletransformers (==0.63.9)
Requires-Dist: linkify-it-py
